Workbook
Name CAPEXPCT: 'Assumption sheet '!$C$10
Name DEpreciationpct: 'Assumption sheet '!$C$9
Name DIscountrate: 'Assumption sheet '!$C$5
Name EBITMargin: 'Assumption sheet '!$C$8
Name REvenuegrowthRate: 'Assumption sheet '!$C$7
Name Taxrate: 'Assumption sheet '!$C$6
Name WCpct: 'Assumption sheet '!$C$11

Sheet Assumption sheet 
B3: Assumption Sheet
B4: A (Input) | C4: B (Value) | D4: C (Notes)
B5: Discount Rate (WACC) | C5: 0.1 | D5: Weighted Average Cost of Capital
B6: Tax Rate | C6: 0.25 | D6: Effective tax rate
B7: Revenue Growth Rate | C7: 0.08 | D7: Yearly projection growth
B8: EBIT Margin | C8: 0.15 | D8: Historical average or assumption
B9: Depreciation as % of Revenue | C9: 0.03 | D9: Historical trend
B10: CAPEX as % of Revenue | C10: 0.05 | D10: Historical trend
B11: Working Capital % of Revenue | C11: 0.1 | D11: Accounts receivable + inventory - payables

Sheet Historical Financial sheet 
A1: Income Statement
A2: A | B2: B (2020) | C2: C (2021) | D2: D (2022)
A3: Revenue | B3: 56585 | C3: 64390 | D3: 67070
A4: COGS | B4: 43800 | C4: 49100 | D4: 51200 | G4: Margin and Ratio
A5: Gross Profit | B5: 12785 | C5: 15290 | D5: 15870 | G5: Year | H5: 2020 | I5: 2021 | J5: 2022
A6: OPEX | B6: 6200 | C6: 6500 | D6: 6800 | G6: Gross Margin | H6: =B5/B3 -> 0.22594327 | I6: =C5/C3 -> 0.23745923 | J6: =D5/D3 -> 0.23661846
A7: EBITDA | B7: 6585 | C7: 8790 | D7: 9070 | G7: Ebidta Margin | H7: =B7/B3 -> 0.1163736 | I7: =C7/C3 -> 0.13651188 | J7: =D7/D3 -> 0.13523185
A8: Depreciation | B8: 1200 | C8: 1250 | D8: 1300 | G8: Net Margin | H8: =B13/B3 -> 0.064752143 | I8: =C13/C3 -> 0.081410157 | J8: =D13/D3 -> 0.080184881
A9: EBIT | B9: 5385 | C9: 7540 | D9: 7770
A10: Interest | B10: 500 | C10: 550 | D10: 600
A11: EBT | B11: 4885 | C11: 6990 | D11: 7170
A12: Taxes | B12: 1221 | C12: 1748 | D12: 1792
A13: Net Income | B13: 3664 | C13: 5242 | D13: 5378
A15: Balance Sheet
A16: A | B16: B (2020) | C16: C (2021) | D16: D (2022)
A17: Cash & Equivalents | B17: 8802 | C17: 7832 | D17: 7500
A18: Accounts Receivable | B18: 5000 | C18: 5200 | D18: 5400
A19: Inventory | B19: 3000 | C19: 3200 | D19: 3400
A20: PP&E | B20: 10000 | C20: 10500 | D20: 11000
A21: Total Assets | B21: 30000 | C21: 31000 | D21: 32000
A22: Debt | B22: 10000 | C22: 10500 | D22: 11000
A23: Accounts Payable | B23: 4000 | C23: 4200 | D23: 4400
A24: Total Liabilities | B24: 14000 | C24: 14700 | D24: 15400
A25: Equity | B25: 16000 | C25: 16300 | D25: 16600
A26: Total Liabilities + Equity | B26: 30000 | C26: 31000 | D26: 32000
A27: working capital | B27: =B18+B19-B23 -> 4000 | C27: =C18+C19-C23 -> 4200 | D27: =D18+D19-D23 -> 4400
A29: Cash flow
A30: A | B30: B (2020) | C30: C (2021) | D30: D (2022)
A31: Operating Cash Flow | B31: 7883 | C31: 7159 | D31: 5847
A32: CAPEX | B32: 1500 | C32: 1600 | D32: 1700
A33: Free Cash Flow | B33: 6383 | C33: 5559 | D33: 4147

Sheet Projection sheet 
B1: Projection Sheet
B2: A (Line Item) | C2: 2023 | D2: 2024 | E2: 2025 | F2: 2026 | G2: 2027
B3: Revenue | C3: ='Historical Financial sheet '!$D3*(1+REvenuegrowthRate) -> 72435.6 | D3: =C3*(1+REvenuegrowthRate) -> 78230.448 | E3: =D3*(1+REvenuegrowthRate) -> 84488.884 | F3: =E3*(1+REvenuegrowthRate) -> 91247.995 | G3: =F3*(1+REvenuegrowthRate) -> 98547.834
B4: Cost of Goods Sold (COGS) | C4: ='Projection sheet '!C3*('Historical Financial sheet '!$D4/'Historical Financial sheet '!D3) -> 55296 | D4: =D3*('Historical Financial sheet '!$D4/'Historical Financial sheet '!$D$3) -> 59719.68 | E4: =E3*('Historical Financial sheet '!$D4/'Historical Financial sheet '!$D$3) -> 64497.254 | F4: =F3*('Historical Financial sheet '!$D4/'Historical Financial sheet '!$D$3) -> 69657.035 | G4: =G3*('Historical Financial sheet '!$D4/'Historical Financial sheet '!$D$3) -> 75229.598
B5: Gross Profit | C5: =C3-C4 -> 17139.6 | D5: =D3-D4 -> 18510.768 | E5: =E3-E4 -> 19991.629 | F5: =F3-F4 -> 21590.96 | G5: =G3-G4 -> 23318.237
B6: Operating Expenses (OPEX) | C6: =C3*('Historical Financial sheet '!$D6/'Historical Financial sheet '!D3) -> 7344 | D6: =D3*('Historical Financial sheet '!$D6/'Historical Financial sheet '!$D$3) -> 7931.52 | E6: =E3*('Historical Financial sheet '!$D6/'Historical Financial sheet '!$D$3) -> 8566.0416 | F6: =F3*('Historical Financial sheet '!$D6/'Historical Financial sheet '!$D$3) -> 9251.3249 | G6: =G3*('Historical Financial sheet '!$D6/'Historical Financial sheet '!$D$3) -> 9991.4309
B7: EBITDA | C7: =C5-C6 -> 9795.6 | D7: =D5-D6 -> 10579.248 | E7: =E5-E6 -> 11425.588 | F7: =F5-F6 -> 12339.635 | G7: =G5-G6 -> 13326.806
B8: Depreciation & Amortization | C8: =C3*DEpreciationpct -> 2173.068 | D8: =D3*DEpreciationpct -> 2346.9134 | E8: =E3*DEpreciationpct -> 2534.6665 | F8: =F3*DEpreciationpct -> 2737.4398 | G8: =G3*DEpreciationpct -> 2956.435
B9: EBIT | C9: =C7-C8 -> 7622.532 | D9: =D7-D8 -> 8232.3346 | E9: =E7-E8 -> 8890.9213 | F9: =F7-F8 -> 9602.195 | G9: =G7-G8 -> 10370.371
B10: Taxes | C10: =IF(C9>0,C9*Taxrate,0) -> 1905.633 | D10: =IF(D9>0,D9*Taxrate,0) -> 2058.0836 | E10: =IF(E9>0,E9*Taxrate,0) -> 2222.7303 | F10: =IF(F9>0,F9*Taxrate,0) -> 2400.5488 | G10: =IF(G9>0,G9*Taxrate,0) -> 2592.5927
B11: Net Income | C11: =C9-C10 -> 5716.899 | D11: =D9-D10 -> 6174.2509 | E11: =E9-E10 -> 6668.191 | F11: =F9-F10 -> 7201.6463 | G11: =G9-G10 -> 7777.778
B12: Working Capital | C12: =(C3*WCpct) -> 7243.56 | D12: =D3*WCpct-'Historical Financial sheet '!E27 -> 7823.0448 | E12: =E3*WCpct-'Historical Financial sheet '!F27 -> 8448.8884 | F12: =F3*WCpct-'Historical Financial sheet '!G27 -> 9124.7995 | G12: =G3*WCpct-'Historical Financial sheet '!H27 -> 9854.7834
B13: CAPEX | C13: =C3*CAPEXPCT -> 3621.78 | D13: =D3*CAPEXPCT -> 3911.5224 | E13: =E3*CAPEXPCT -> 4224.4442 | F13: =F3*CAPEXPCT -> 4562.3997 | G13: =G3*CAPEXPCT -> 4927.3917
B14: Chng In Working Capital | C14: =C12-'Historical Financial sheet '!D27 -> 2843.56 | D14: =D12-C12 -> 579.4848 | E14: =E12-D12 -> 625.84358 | F14: =F12-E12 -> 675.91107 | G14: =G12-F12 -> 729.98396
B15: Free Cash Flow (FCF) | C15: =C11+C8-C13-C14 -> 1424.627 | D15: =D11+D8-D13-D14 -> 4030.1572 | E15: =E11+E8-E13-E14 -> 4352.5697 | F15: =F11+F8-F13-F14 -> 4700.7753 | G15: =G11+G8-G13-G14 -> 5076.8373

Sheet DCF valuation
B3: DCF Valuation
B4: Iteam | C4: 2023 | D4: 2024 | E4: 2025 | F4: 2026 | G4: 2027
B5: Free Cash Flow (FCF) | C5: ='Projection sheet '!C15 -> 1424.627 | D5: ='Projection sheet '!D15 -> 4030.1572 | E5: ='Projection sheet '!E15 -> 4352.5697 | F5: ='Projection sheet '!F15 -> 4700.7753 | G5: ='Projection sheet '!G15 -> 5076.8373
B6: Discount factors | C6: =1/(1+DIscountrate)^1 -> 0.90909091 | D6: =1/(1+DIscountrate)^2 -> 0.82644628 | E6: =1/(1+DIscountrate)^3 -> 0.7513148 | F6: =1/(1+DIscountrate)^4 -> 0.68301346 | G6: =1/(1+DIscountrate)^5 -> 0.62092132
B7: Present Value of FCF | C7: =C5*C6 -> 1295.1155 | D7: =D5*D6 -> 3330.7084 | E7: =E5*E6 -> 3270.1501 | F7: =F5*F6 -> 3210.6928 | G7: =G5*G6 -> 3152.3166
B8: Terminal value | G8: =G5*(1+0.03)/(DIscountrate-0.03) -> 74702.035
B9: PV Of terminal | G9: =G8/(1+DIscountrate)^5 -> 46384.086
B10: Enterprise value | G10: =C7+D7+E7+F7+G7+G9 -> 60643.07
